processor_core/components/registers/register.v
// ============================================================
// register.v : generic parameterised register (default 32 bit)
// Purpose : basic storage element with synchronous reset and
//           write enable. Reused later for pipeline registers.
// ============================================================
`timescale 1ns/1ps
module register #(
    parameter WIDTH = 32,
    parameter RESET_VALUE = 0
)(
    input  wire             clk,
    input  wire             rst,     // synchronous, active high
    input  wire             en,      // load enable
    input  wire [WIDTH-1:0] d,
    output reg  [WIDTH-1:0] q
);
    always @(posedge clk) begin
        if (rst)     q <= RESET_VALUE;
        else if (en) q <= d;
    end
endmodule

processor_core/register_transfer_design/rtl-with-control-unit/rtl/processor_core/components/registers/register-tb.v
`timescale 1ns/1ps
module register_tb;
    reg         clk = 0, rst = 1, en = 0;
    reg  [31:0] d = 0;
    wire [31:0] q;
    integer errors = 0;

    register dut (.clk(clk), .rst(rst), .en(en), .d(d), .q(q));
    always #5 clk = ~clk;

    task expect_q(input [31:0] expected, input [127:0] name);
        begin
            if (q !== expected) begin
                $display("FAIL %0s: q=%h expected=%h", name, q, expected);
                errors = errors + 1;
            end else $display("PASS %0s", name);
        end
    endtask

    initial begin
        $dumpfile("register.vcd");
        $dumpvars(0, register_tb);

        @(posedge clk); #1; expect_q(32'h0, "reset clears");
        rst = 0; d = 32'hDEADBEEF; en = 0;
        @(posedge clk); #1; expect_q(32'h0, "ignores d when en=0");
        en = 1;
        @(posedge clk); #1; expect_q(32'hDEADBEEF, "loads d when en=1");
        d = 32'h12345678; en = 0;
        @(posedge clk); #1; expect_q(32'hDEADBEEF, "holds value");
        rst = 1;
        @(posedge clk); #1; expect_q(32'h0, "reset again");

        if (errors == 0) $display("REGISTER: ALL TESTS PASSED");
        else             $display("REGISTER: %0d TEST(S) FAILED", errors);
        $finish;
    end
endmodule

processor_core/components/registers/register.vcd
$date
	Fri Oct  2 11:16:25 2026
$end
$version
	Icarus Verilog
$end
$timescale
	1ps
$end
$scope module register_tb $end
$var wire 32 ! q [31:0] $end
$var reg 1 " clk $end
$var reg 32 # d [31:0] $end
$var reg 1 $ en $end
$var reg 1 % rst $end
$var integer 32 & errors [31:0] $end
$scope module dut $end
$var wire 1 " clk $end
$var wire 32 ' d [31:0] $end
$var wire 1 $ en $end
$var wire 1 % rst $end
$var parameter 32 ( RESET_VALUE $end
$var parameter 32 ) WIDTH $end
$var reg 32 * q [31:0] $end
$upscope $end
$scope task expect_q $end
$var reg 32 + expected [31:0] $end
$var reg 128 , name [127:0] $end
$upscope $end
$upscope $end
$enddefinitions $end
$comment Show the parameter values. $end
$dumpall
b100000 )
b0 (
$end
#0
$dumpvars
bx ,
bx +
bx *
b0 '
b0 &
1%
0$
b0 #
0"
bx !
$end
#5000
b0 !
b0 *
1"
#6000
b11011110101011011011111011101111 #
b11011110101011011011111011101111 '
0%
b11100100110010101110011011001010111010000100000011000110110110001100101011000010111001001110011 ,
b0 +
#10000
0"
#15000
1"
#16000
1$
b1101111011100100110010101110011001000000110010000100000011101110110100001100101011011100010000001100101011011100011110100110000 ,
#20000
0"
#25000
b11011110101011011011111011101111 !
b11011110101011011011111011101111 *
1"
#26000
0$
b10010001101000101011001111000 #
b10010001101000101011001111000 '
b1101111011000010110010001110011001000000110010000100000011101110110100001100101011011100010000001100101011011100011110100110001 ,
b11011110101011011011111011101111 +
#30000
0"
#35000
1"
#36000
1%
b110100001101111011011000110010001110011001000000111011001100001011011000111010101100101 ,
#40000
0"
#45000
b0 !
b0 *
1"
#46000
b111001001100101011100110110010101110100001000000110000101100111011000010110100101101110 ,
b0 +
