processor_core/components/alu/alu.v
// ============================================================
// alu.v : 32-bit Arithmetic Logic Unit for RV32I
// Purpose : performs every arithmetic / logic / shift / compare
//           operation the core needs. Purely combinational.
// ============================================================
`timescale 1ns/1ps
module alu #(
    parameter WIDTH = 32
)(
    input  wire [WIDTH-1:0] a,        // operand A (rs1 or PC)
    input  wire [WIDTH-1:0] b,        // operand B (rs2 or immediate)
    input  wire [3:0]       alu_op,   // operation select (see below)
    output reg  [WIDTH-1:0] result,
    output wire             zero      // 1 when result == 0
);
    // ALU operation codes (shared with the control unit)
    localparam ALU_ADD  = 4'b0000;
    localparam ALU_SUB  = 4'b0001;
    localparam ALU_SLL  = 4'b0010;
    localparam ALU_SLT  = 4'b0011;   // signed   less-than
    localparam ALU_SLTU = 4'b0100;   // unsigned less-than
    localparam ALU_XOR  = 4'b0101;
    localparam ALU_SRL  = 4'b0110;   // logical    shift right
    localparam ALU_SRA  = 4'b0111;   // arithmetic shift right
    localparam ALU_OR   = 4'b1000;
    localparam ALU_AND  = 4'b1001;

    wire [4:0] shamt = b[4:0];       // RV32I shifts use only the low 5 bits

    always @(*) begin
        case (alu_op)
            ALU_ADD : result = a + b;
            ALU_SUB : result = a - b;
            ALU_SLL : result = a << shamt;
            ALU_SLT : result = ($signed(a) < $signed(b)) ? {{(WIDTH-1){1'b0}},1'b1} : {WIDTH{1'b0}};
            ALU_SLTU: result = (a < b)                   ? {{(WIDTH-1){1'b0}},1'b1} : {WIDTH{1'b0}};
            ALU_XOR : result = a ^ b;
            ALU_SRL : result = a >> shamt;
            ALU_SRA : result = $signed(a) >>> shamt;
            ALU_OR  : result = a | b;
            ALU_AND : result = a & b;
            default : result = {WIDTH{1'b0}};
        endcase
    end

    assign zero = (result == {WIDTH{1'b0}});
endmodule

processor_core/components/alu/alu-tb.v
`timescale 1ns/1ps
module alu_tb;
    reg  [31:0] a, b;
    reg  [3:0]  alu_op;
    wire [31:0] result;
    wire        zero;
    integer errors = 0;

    alu dut (.a(a), .b(b), .alu_op(alu_op), .result(result), .zero(zero));

    task check(input [3:0] op, input [31:0] x, y, input [31:0] expected, input [127:0] name);
        begin
            alu_op = op; a = x; b = y; #10;
            if (result !== expected) begin
                $display("FAIL %0s: a=%h b=%h got=%h expected=%h", name, x, y, result, expected);
                errors = errors + 1;
            end else
                $display("PASS %0s", name);
        end
    endtask

    initial begin
        $dumpfile("alu.vcd");
        $dumpvars(0, alu_tb);

        check(4'b0000, 32'd10,        32'd20,        32'd30,        "ADD");
        check(4'b0000, 32'hFFFFFFFF,  32'd1,         32'd0,         "ADD wrap");
        check(4'b0001, 32'd20,        32'd5,         32'd15,        "SUB");
        check(4'b0001, 32'd5,         32'd20,        32'hFFFFFFF1,  "SUB negative");
        check(4'b0010, 32'd1,         32'd4,         32'd16,        "SLL");
        check(4'b0011, 32'hFFFFFFFF,  32'd1,         32'd1,         "SLT (-1<1)");
        check(4'b0011, 32'd1,         32'hFFFFFFFF,  32'd0,         "SLT (1<-1)");
        check(4'b0100, 32'hFFFFFFFF,  32'd1,         32'd0,         "SLTU");
        check(4'b0100, 32'd1,         32'hFFFFFFFF,  32'd1,         "SLTU 2");
        check(4'b0101, 32'hF0F0F0F0,  32'hFFFF0000,  32'h0F0FF0F0,  "XOR");
        check(4'b0110, 32'h80000000,  32'd4,         32'h08000000,  "SRL");
        check(4'b0111, 32'h80000000,  32'd4,         32'hF8000000,  "SRA");
        check(4'b0110, 32'h00000010,  32'd36,        32'h00000001,  "SRL uses low 5 bits");
        check(4'b1000, 32'hF0F0F0F0,  32'h0F0F0F0F,  32'hFFFFFFFF,  "OR");
        check(4'b1001, 32'hF0F0F0F0,  32'hFFFF0000,  32'hF0F00000,  "AND");

        // zero flag
        alu_op = 4'b0001; a = 32'd7; b = 32'd7; #10;
        if (zero !== 1'b1) begin $display("FAIL zero flag"); errors = errors + 1; end
        else $display("PASS zero flag");

        if (errors == 0) $display("ALU: ALL TESTS PASSED");
        else             $display("ALU: %0d TEST(S) FAILED", errors);
        $finish;
    end
endmodule

processor_core/components/alu/alu.vcd
$date
	Fri Oct  2 14:13:49 2026
$end
$version
	Icarus Verilog
$end
$timescale
	1ps
$end
$scope module alu_tb $end
$var wire 1 ! zero $end
$var wire 32 " result [31:0] $end
$var reg 32 # a [31:0] $end
$var reg 4 $ alu_op [3:0] $end
$var reg 32 % b [31:0] $end
$var integer 32 & errors [31:0] $end
$scope module dut $end
$var wire 32 ' a [31:0] $end
$var wire 4 ( alu_op [3:0] $end
$var wire 32 ) b [31:0] $end
$var wire 1 ! zero $end
$var wire 5 * shamt [4:0] $end
$var parameter 4 + ALU_ADD $end
$var parameter 4 , ALU_AND $end
$var parameter 4 - ALU_OR $end
$var parameter 4 . ALU_SLL $end
$var parameter 4 / ALU_SLT $end
$var parameter 4 0 ALU_SLTU $end
$var parameter 4 1 ALU_SRA $end
$var parameter 4 2 ALU_SRL $end
$var parameter 4 3 ALU_SUB $end
$var parameter 4 4 ALU_XOR $end
$var parameter 32 5 WIDTH $end
$var reg 32 6 result [31:0] $end
$upscope $end
$scope task check $end
$var reg 32 7 expected [31:0] $end
$var reg 128 8 name [127:0] $end
$var reg 4 9 op [3:0] $end
$var reg 32 : x [31:0] $end
$var reg 32 ; y [31:0] $end
$upscope $end
$upscope $end
$enddefinitions $end
$comment Show the parameter values. $end
$dumpall
b100000 5
b101 4
b1 3
b110 2
b111 1
b100 0
b11 /
b10 .
b1000 -
b1001 ,
b0 +
$end
#0
$dumpvars
b10100 ;
b1010 :
b0 9
b10000010100010001000100 8
b11110 7
b11110 6
b10100 *
b10100 )
b0 (
b1010 '
b0 &
b10100 %
b0 $
b1010 #
b11110 "
0!
$end
#10000
b1 *
1!
b0 "
b0 6
b1 %
b1 )
b11111111111111111111111111111111 #
b11111111111111111111111111111111 '
b100000101000100010001000010000001110111011100100110000101110000 8
b0 7
b1 ;
b11111111111111111111111111111111 :
#20000
b101 *
0!
b1111 "
b1111 6
b101 %
b101 )
b10100 #
b10100 '
b1 $
b1 (
b10100110101010101000010 8
b1111 7
b101 ;
b10100 :
b1 9
#30000
b10100 *
b11111111111111111111111111110001 "
b11111111111111111111111111110001 6
b10100 %
b10100 )
b101 #
b101 '
b10100110101010101000010001000000110111001100101011001110110000101110100011010010111011001100101 8
b11111111111111111111111111110001 7
b10100 ;
b101 :
#40000
b100 *
b10000 "
b10000 6
b100 %
b100 )
b1 #
b1 '
b10 $
b10 (
b10100110100110001001100 8
b10000 7
b100 ;
b1 :
b10 9
#50000
b1 *
b1 "
b1 6
b1 %
b1 )
b11111111111111111111111111111111 #
b11111111111111111111111111111111 '
b11 $
b11 (
b1010011010011000101010000100000001010000010110100110001001111000011000100101001 8
b1 7
b1 ;
b11111111111111111111111111111111 :
b11 9
#60000
b11111 *
1!
b0 "
b0 6
b11111111111111111111111111111111 %
b11111111111111111111111111111111 )
b1 #
b1 '
b1010011010011000101010000100000001010000011000100111100001011010011000100101001 8
b0 7
b11111111111111111111111111111111 ;
b1 :
#70000
b1 *
b1 %
b1 )
b11111111111111111111111111111111 #
b11111111111111111111111111111111 '
b100 $
b100 (
b1010011010011000101010001010101 8
b1 ;
b11111111111111111111111111111111 :
b100 9
#80000
b11111 *
0!
b1 "
b1 6
b11111111111111111111111111111111 %
b11111111111111111111111111111111 )
b1 #
b1 '
b10100110100110001010100010101010010000000110010 8
b1 7
b11111111111111111111111111111111 ;
b1 :
#90000
b0 *
b1111000011111111000011110000 "
b1111000011111111000011110000 6
b11111111111111110000000000000000 %
b11111111111111110000000000000000 )
b11110000111100001111000011110000 #
b11110000111100001111000011110000 '
b101 $
b101 (
b10110000100111101010010 8
b1111000011111111000011110000 7
b11111111111111110000000000000000 ;
b11110000111100001111000011110000 :
b101 9
#100000
b100 *
b1000000000000000000000000000 "
b1000000000000000000000000000 6
b100 %
b100 )
b10000000000000000000000000000000 #
b10000000000000000000000000000000 '
b110 $
b110 (
b10100110101001001001100 8
b1000000000000000000000000000 7
b100 ;
b10000000000000000000000000000000 :
b110 9
#110000
b11111000000000000000000000000000 "
b11111000000000000000000000000000 6
b111 $
b111 (
b10100110101001001000001 8
b11111000000000000000000000000000 7
b111 9
#120000
b1 "
b1 6
b100100 %
b100100 )
b10000 #
b10000 '
b110 $
b110 (
b100000011101010111001101100101011100110010000001101100011011110111011100100000001101010010000001100010011010010111010001110011 8
b1 7
b100100 ;
b10000 :
b110 9
#130000
b1111 *
b11111111111111111111111111111111 "
b11111111111111111111111111111111 6
b1111000011110000111100001111 %
b1111000011110000111100001111 )
b11110000111100001111000011110000 #
b11110000111100001111000011110000 '
b1000 $
b1000 (
b100111101010010 8
b11111111111111111111111111111111 7
b1111000011110000111100001111 ;
b11110000111100001111000011110000 :
b1000 9
#140000
b0 *
b11110000111100000000000000000000 "
b11110000111100000000000000000000 6
b11111111111111110000000000000000 %
b11111111111111110000000000000000 )
b1001 $
b1001 (
b10000010100111001000100 8
b11110000111100000000000000000000 7
b11111111111111110000000000000000 ;
b1001 9
#150000
b111 *
1!
b0 "
b0 6
b111 %
b111 )
b111 #
b111 '
b1 $
b1 (
