processor_core/components/memory_devices/data-memory.v
// ============================================================
// data-memory.v : byte-addressable data RAM (little endian)
// Purpose : holds program data. Supports the RV32I load/store
//           widths, selected by funct3:
//             store: 000 SB, 001 SH, 010 SW
//             load : 000 LB, 001 LH, 010 LW, 100 LBU, 101 LHU
//           Write is synchronous; read is combinational.
//           Addresses are expected to be naturally aligned.
// ============================================================
`timescale 1ns/1ps
module data_memory #(
    parameter SIZE_BYTES = 4096
)(
    input  wire        clk,
    input  wire        mem_write,
    input  wire        mem_read,
    input  wire [2:0]  funct3,
    input  wire [31:0] addr,
    input  wire [31:0] wdata,
    output reg  [31:0] rdata
);
    reg [7:0] mem [0:SIZE_BYTES-1];
    integer i;

    initial begin
        for (i = 0; i < SIZE_BYTES; i = i + 1) mem[i] = 8'h00;
    end

    wire [31:0] a = addr % SIZE_BYTES;

    // ---------- write ----------
    always @(posedge clk) begin
        if (mem_write) begin
            mem[a] <= wdata[7:0];
            if (funct3[1:0] != 2'b00) mem[a+1] <= wdata[15:8];   // SH, SW
            if (funct3[1:0] == 2'b10) begin                      // SW
                mem[a+2] <= wdata[23:16];
                mem[a+3] <= wdata[31:24];
            end
        end
    end

    // ---------- read ----------
    always @(*) begin
        rdata = 32'b0;
        if (mem_read) begin
            case (funct3)
                3'b000: rdata = {{24{mem[a][7]}}, mem[a]};                                  // LB
                3'b001: rdata = {{16{mem[a+1][7]}}, mem[a+1], mem[a]};                      // LH
                3'b010: rdata = {mem[a+3], mem[a+2], mem[a+1], mem[a]};                     // LW
                3'b100: rdata = {24'b0, mem[a]};                                            // LBU
                3'b101: rdata = {16'b0, mem[a+1], mem[a]};                                  // LHU
                default: rdata = 32'b0;
            endcase
        end
    end
endmodule

processor_core/register_transfer_design/rtl-with-control-unit/rtl/processor_core/components/memory_devices/data-memory-tb.v
`timescale 1ns/1ps
module data_memory_tb;
    reg         clk = 0, mem_write = 0, mem_read = 0;
    reg  [2:0]  funct3 = 0;
    reg  [31:0] addr = 0, wdata = 0;
    wire [31:0] rdata;
    integer errors = 0;

    data_memory #(.SIZE_BYTES(256)) dut (.clk(clk), .mem_write(mem_write), .mem_read(mem_read),
        .funct3(funct3), .addr(addr), .wdata(wdata), .rdata(rdata));
    always #5 clk = ~clk;

    task store(input [2:0] f, input [31:0] a, input [31:0] d);
        begin
            funct3 = f; addr = a; wdata = d; mem_write = 1; mem_read = 0;
            @(posedge clk); #1; mem_write = 0;
        end
    endtask

    task load_check(input [2:0] f, input [31:0] a, input [31:0] expected, input [127:0] name);
        begin
            funct3 = f; addr = a; mem_read = 1; #1;
            if (rdata !== expected) begin
                $display("FAIL %0s: got %h expected %h", name, rdata, expected);
                errors = errors + 1;
            end else $display("PASS %0s", name);
            mem_read = 0;
        end
    endtask

    initial begin
        $dumpfile("data_memory.vcd");
        $dumpvars(0, data_memory_tb);

        store(3'b010, 32'h10, 32'hA1B2C3D4);                 // SW
        load_check(3'b010, 32'h10, 32'hA1B2C3D4, "LW");
        load_check(3'b000, 32'h10, 32'hFFFFFFD4, "LB sign-extend (little endian)");
        load_check(3'b100, 32'h10, 32'h000000D4, "LBU zero-extend");
        load_check(3'b001, 32'h10, 32'hFFFFC3D4, "LH sign-extend");
        load_check(3'b101, 32'h10, 32'h0000C3D4, "LHU zero-extend");
        load_check(3'b000, 32'h13, 32'hFFFFFFA1, "LB top byte");

        store(3'b000, 32'h20, 32'h0000007F);                 // SB
        load_check(3'b010, 32'h20, 32'h0000007F, "SB writes one byte only");
        store(3'b001, 32'h24, 32'h0000BEEF);                 // SH
        load_check(3'b010, 32'h24, 32'h0000BEEF, "SH writes two bytes only");

        // read disabled gives zero
        mem_read = 0; addr = 32'h10; #1;
        if (rdata !== 32'b0) begin $display("FAIL read disabled"); errors = errors + 1; end
        else $display("PASS read disabled returns 0");

        if (errors == 0) $display("DATA MEMORY: ALL TESTS PASSED");
        else             $display("DATA MEMORY: %0d TEST(S) FAILED", errors);
        $finish;
    end
endmodule

processor_core/components/memory_devices/data_memory.vcd
$date
	Fri Oct  2 11:16:25 2026
$end
$version
	Icarus Verilog
$end
$timescale
	1ps
$end
$scope module data_memory_tb $end
$var wire 32 ! rdata [31:0] $end
$var reg 32 " addr [31:0] $end
$var reg 1 # clk $end
$var reg 3 $ funct3 [2:0] $end
$var reg 1 % mem_read $end
$var reg 1 & mem_write $end
$var reg 32 ' wdata [31:0] $end
$var integer 32 ( errors [31:0] $end
$scope module dut $end
$var wire 32 ) addr [31:0] $end
$var wire 1 # clk $end
$var wire 3 * funct3 [2:0] $end
$var wire 1 % mem_read $end
$var wire 1 & mem_write $end
$var wire 32 + wdata [31:0] $end
$var wire 32 , a [31:0] $end
$var parameter 32 - SIZE_BYTES $end
$var reg 32 . rdata [31:0] $end
$var integer 32 / i [31:0] $end
$upscope $end
$scope task load_check $end
$var reg 32 0 a [31:0] $end
$var reg 32 1 expected [31:0] $end
$var reg 3 2 f [2:0] $end
$var reg 128 3 name [127:0] $end
$upscope $end
$scope task store $end
$var reg 32 4 a [31:0] $end
$var reg 32 5 d [31:0] $end
$var reg 3 6 f [2:0] $end
$upscope $end
$upscope $end
$enddefinitions $end
$comment Show the parameter values. $end
$dumpall
b100000000 -
$end
#0
$dumpvars
b10 6
b10100001101100101100001111010100 5
b10000 4
bx 3
bx 2
bx 1
bx 0
b100000000 /
b0 .
b10000 ,
b10100001101100101100001111010100 +
b10 *
b10000 )
b0 (
b10100001101100101100001111010100 '
1&
0%
b10 $
0#
b10000 "
b0 !
$end
#5000
1#
#6000
b10100001101100101100001111010100 !
b10100001101100101100001111010100 .
1%
b100110001010111 3
b10100001101100101100001111010100 1
b10000 0
b10 2
0&
#7000
b11111111111111111111111111010100 !
b11111111111111111111111111010100 .
b0 $
b0 *
b100000001010000110110001101001011101000111010001101100011001010010000001100101011011100110010001101001011000010110111000101001 3
b11111111111111111111111111010100 1
b0 2
1%
#8000
b11010100 !
b11010100 .
b100 $
b100 *
b10011000100001001010101001000000111101001100101011100100110111100101101011001010111100001110100011001010110111001100100 3
b11010100 1
b100 2
1%
#9000
b11111111111111111100001111010100 !
b11111111111111111100001111010100 .
b1 $
b1 *
b100110001001000001000000111001101101001011001110110111000101101011001010111100001110100011001010110111001100100 3
b11111111111111111100001111010100 1
b1 2
1%
#10000
b1100001111010100 !
b1100001111010100 .
b101 $
b101 *
b10011000100100001010101001000000111101001100101011100100110111100101101011001010111100001110100011001010110111001100100 3
b1100001111010100 1
b101 2
1%
0#
#11000
b11111111111111111111111110100001 !
b11111111111111111111111110100001 .
b10011 ,
b10011 "
b10011 )
b0 $
b0 *
b100110001000010001000000111010001101111011100000010000001100010011110010111010001100101 3
b11111111111111111111111110100001 1
b10011 0
b0 2
1%
#12000
b0 !
b0 .
1&
b1111111 '
b1111111 +
b100000 ,
b100000 "
b100000 )
b1111111 5
b100000 4
b0 6
0%
#15000
1#
#16000
b1111111 !
b1111111 .
1%
b10 $
b10 *
b1100101011100110010000001101111011011100110010100100000011000100111100101110100011001010010000001101111011011100110110001111001 3
b1111111 1
b100000 0
b10 2
0&
#17000
b0 !
b0 .
1&
b1011111011101111 '
b1011111011101111 +
b100100 ,
b100100 "
b100100 )
b1 $
b1 *
b1011111011101111 5
b100100 4
b1 6
0%
#20000
0#
#25000
1#
#26000
b1011111011101111 !
b1011111011101111 .
1%
b10 $
b10 *
b1110011001000000111010001110111011011110010000001100010011110010111010001100101011100110010000001101111011011100110110001111001 3
b1011111011101111 1
b100100 0
0&
#27000
b0 !
b0 .
b10000 ,
b10000 "
b10000 )
0%
