processor_core/components/program_counter/pc.v
// ============================================================
// program-counter.v : 32-bit program counter
// Purpose : holds the address of the current instruction.
//           On each clock it loads next_pc (PC+4, branch or jump target).
//           Synchronous, active-high reset.
// ============================================================
`timescale 1ns/1ps
module program_counter #(
    parameter WIDTH      = 32,
    parameter RESET_ADDR = 32'h0000_0000
)(
    input  wire             clk,
    input  wire             rst,        // synchronous reset
    input  wire             en,         // 0 = hold (used for stalls later)
    input  wire [WIDTH-1:0] next_pc,
    output reg  [WIDTH-1:0] pc,
    output wire [WIDTH-1:0] pc_plus4
);
    assign pc_plus4 = pc + 32'd4;

    always @(posedge clk) begin
        if (rst)     pc <= RESET_ADDR;
        else if (en) pc <= next_pc;
    end
endmodule

processor_core/components/program_counter/program-counter-tb.v
`timescale 1ns/1ps
module program_counter_tb;
    reg         clk = 0, rst = 1, en = 1;
    reg  [31:0] next_pc = 0;
    wire [31:0] pc, pc_plus4;
    integer errors = 0;

    program_counter dut (.clk(clk), .rst(rst), .en(en), .next_pc(next_pc), .pc(pc), .pc_plus4(pc_plus4));

    always #5 clk = ~clk;

    task expect_pc(input [31:0] expected, input [127:0] name);
        begin
            if (pc !== expected) begin
                $display("FAIL %0s: pc=%h expected=%h", name, pc, expected);
                errors = errors + 1;
            end else $display("PASS %0s", name);
        end
    endtask

    initial begin
        $dumpfile("program_counter.vcd");
        $dumpvars(0, program_counter_tb);

        @(posedge clk); #1; expect_pc(32'h0, "reset value");
        rst = 0;

        // sequential fetch: next_pc follows pc_plus4
        repeat (3) begin
            next_pc = pc_plus4;
            @(posedge clk); #1;
        end
        expect_pc(32'h0000000C, "three sequential steps");

        // branch / jump
        next_pc = 32'h0000_0100;
        @(posedge clk); #1; expect_pc(32'h0000_0100, "jump to 0x100");

        // hold when en = 0
        en = 0; next_pc = 32'h0000_0200;
        @(posedge clk); #1; expect_pc(32'h0000_0100, "hold when disabled");

        // reset again
        en = 1; rst = 1;
        @(posedge clk); #1; expect_pc(32'h0, "reset again");

        if (errors == 0) $display("PROGRAM COUNTER: ALL TESTS PASSED");
        else             $display("PROGRAM COUNTER: %0d TEST(S) FAILED", errors);
        $finish;
    end
endmodule

processor_core/components/program_counter/program_counter.vcd
$date
	Fri Oct  2 14:13:49 2026
$end
$version
	Icarus Verilog
$end
$timescale
	1ps
$end
$scope module program_counter_tb $end
$var wire 32 ! pc_plus4 [31:0] $end
$var wire 32 " pc [31:0] $end
$var reg 1 # clk $end
$var reg 1 $ en $end
$var reg 32 % next_pc [31:0] $end
$var reg 1 & rst $end
$var integer 32 ' errors [31:0] $end
$scope module dut $end
$var wire 1 # clk $end
$var wire 1 $ en $end
$var wire 32 ( next_pc [31:0] $end
$var wire 1 & rst $end
$var wire 32 ) pc_plus4 [31:0] $end
$var parameter 32 * RESET_ADDR $end
$var parameter 32 + WIDTH $end
$var reg 32 , pc [31:0] $end
$upscope $end
$scope task expect_pc $end
$var reg 32 - expected [31:0] $end
$var reg 128 . name [127:0] $end
$upscope $end
$upscope $end
$enddefinitions $end
$comment Show the parameter values. $end
$dumpall
b100000 +
b0 *
$end
#0
$dumpvars
bx .
bx -
bx ,
bx )
b0 (
b0 '
1&
b0 %
1$
0#
bx "
bx !
$end
#5000
b100 !
b100 )
b0 "
b0 ,
1#
#6000
b100 %
b100 (
0&
b111001001100101011100110110010101110100001000000111011001100001011011000111010101100101 .
b0 -
#10000
0#
#15000
b1000 !
b1000 )
b100 "
b100 ,
1#
#16000
b1000 %
b1000 (
#20000
0#
#25000
b1100 !
b1100 )
b1000 "
b1000 ,
1#
#26000
b1100 %
b1100 (
#30000
0#
#35000
b10000 !
b10000 )
b1100 "
b1100 ,
1#
#36000
b100000000 %
b100000000 (
b1110011011001010111000101110101011001010110111001110100011010010110000101101100001000000111001101110100011001010111000001110011 .
b1100 -
#40000
0#
#45000
b100000100 !
b100000100 )
b100000000 "
b100000000 ,
1#
#46000
b1000000000 %
b1000000000 (
0$
b1101010011101010110110101110000001000000111010001101111001000000011000001111000001100010011000000110000 .
b100000000 -
#50000
0#
#55000
1#
#56000
1&
1$
b1101100011001000010000001110111011010000110010101101110001000000110010001101001011100110110000101100010011011000110010101100100 .
#60000
0#
#65000
b100 !
b100 )
b0 "
b0 ,
1#
#66000
b111001001100101011100110110010101110100001000000110000101100111011000010110100101101110 .
b0 -
