processor_core/register_transfer_design/rtl-with-control-unit/rtl/processor_core/components/immediate_generators/immediate-generator.v
// ============================================================
// immediate-generator.v : RV32I immediate extractor
// Purpose : RISC-V scatters the immediate bits differently in the
//           I, S, B, U and J formats. This block reassembles them
//           and sign-extends the result to 32 bits.
// ============================================================
`timescale 1ns/1ps
module immediate_generator (
    input  wire [31:0] instr,
    output reg  [31:0] imm
);
    wire [6:0] opcode = instr[6:0];

    always @(*) begin
        case (opcode)
            // I-type: OP-IMM, LOAD, JALR
            7'b0010011,
            7'b0000011,
            7'b1100111: imm = {{20{instr[31]}}, instr[31:20]};
            // S-type: STORE
            7'b0100011: imm = {{20{instr[31]}}, instr[31:25], instr[11:7]};
            // B-type: BRANCH
            7'b1100011: imm = {{19{instr[31]}}, instr[31], instr[7], instr[30:25], instr[11:8], 1'b0};
            // U-type: LUI, AUIPC
            7'b0110111,
            7'b0010111: imm = {instr[31:12], 12'b0};
            // J-type: JAL
            7'b1101111: imm = {{11{instr[31]}}, instr[31], instr[19:12], instr[20], instr[30:21], 1'b0};
            default   : imm = 32'b0;
        endcase
    end
endmodule

processor_core/components/immediate_generators/immediate-generator-tb.v
`timescale 1ns/1ps
module immediate_generator_tb;
    reg  [31:0] instr;
    wire [31:0] imm;
    integer errors = 0;

    immediate_generator dut (.instr(instr), .imm(imm));

    task check(input [31:0] i, input [31:0] expected, input [127:0] name);
        begin
            instr = i; #10;
            if (imm !== expected) begin
                $display("FAIL %0s: instr=%h imm=%h expected=%h", name, i, imm, expected);
                errors = errors + 1;
            end else $display("PASS %0s", name);
        end
    endtask

    initial begin
        $dumpfile("immediate_generator.vcd");
        $dumpvars(0, immediate_generator_tb);

        check(32'h00500093, 32'd5,          "addi x1,x0,5     (I)");
        check(32'hFFF00093, 32'hFFFFFFFF,   "addi x1,x0,-1    (I neg)");
        check(32'h0020A423, 32'd8,          "sw x2,8(x1)      (S)");
        check(32'hFE20AE23, 32'hFFFFFFFC,   "sw x2,-4(x1)     (S neg)");
        check(32'h00208663, 32'd12,         "beq x1,x2,+12    (B)");
        check(32'hFE208EE3, 32'hFFFFFFFC,   "beq x1,x2,-4     (B neg)");
        check(32'h123450B7, 32'h12345000,   "lui x1,0x12345   (U)");
        check(32'h010000EF, 32'd16,         "jal x1,+16       (J)");
        check(32'hFF1FF0EF, 32'hFFFFFFF0,   "jal x1,-16       (J neg)");

        if (errors == 0) $display("IMMEDIATE GENERATOR: ALL TESTS PASSED");
        else             $display("IMMEDIATE GENERATOR: %0d TEST(S) FAILED", errors);
        $finish;
    end
endmodule

processor_core/components/immediate_generator/immediate_generator.vcd
$date
	Fri Oct  2 14:13:49 2026
$end
$version
	Icarus Verilog
$end
$timescale
	1ps
$end
$scope module immediate_generator_tb $end
$var wire 32 ! imm [31:0] $end
$var reg 32 " instr [31:0] $end
$var integer 32 # errors [31:0] $end
$scope module dut $end
$var wire 32 $ instr [31:0] $end
$var wire 7 % opcode [6:0] $end
$var reg 32 & imm [31:0] $end
$upscope $end
$scope task check $end
$var reg 32 ' expected [31:0] $end
$var reg 32 ( i [31:0] $end
$var reg 128 ) name [127:0] $end
$upscope $end
$upscope $end
$enddefinitions $end
$comment Show the parameter values. $end
$dumpall
$end
#0
$dumpvars
b100000011110000011000100101100011110000011000000101100001101010010000000100000001000000010000000100000001010000100100100101001 )
b10100000000000010010011 (
b101 '
b101 &
b10011 %
b10100000000000010010011 $
b0 #
b10100000000000010010011 "
b101 !
$end
#10000
b11111111111111111111111111111111 !
b11111111111111111111111111111111 &
b11111111111100000000000010010011 "
b11111111111100000000000010010011 $
b1111000001100000010110000101101001100010010000000100000001000000010000000101000010010010010000001101110011001010110011100101001 )
b11111111111111111111111111111111 '
b11111111111100000000000010010011 (
#20000
b1000 !
b1000 &
b100011 %
b1000001010010000100011 "
b1000001010010000100011 $
b110010001011000011100000101000011110000011000100101001001000000010000000100000001000000010000000100000001010000101001100101001 )
b1000 '
b1000001010010000100011 (
#30000
b11111111111111111111111111111100 !
b11111111111111111111111111111100 &
b11111110001000001010111000100011 "
b11111110001000001010111000100011 $
b101000011110000011000100101001001000000010000000100000001000000010000000101000010100110010000001101110011001010110011100101001 )
b11111111111111111111111111111100 '
b11111110001000001010111000100011 (
#40000
b1100 !
b1100 &
b1100011 %
b1000001000011001100011 "
b1000001000011001100011 $
b1111000001100010010110001111000001100100010110000101011001100010011001000100000001000000010000000100000001010000100001000101001 )
b1100 '
b1000001000011001100011 (
#50000
b11111111111111111111111111111100 !
b11111111111111111111111111111100 &
b11111110001000001000111011100011 "
b11111110001000001000111011100011 $
b110010001011000010110100110100001000000010000000100000001000000010000000101000010000100010000001101110011001010110011100101001 )
b11111111111111111111111111111100 '
b11111110001000001000111011100011 (
#60000
b10010001101000101000000000000 !
b10010001101000101000000000000 &
b110111 %
b10010001101000101000010110111 "
b10010001101000101000010110111 $
b1111000001100010010110000110000011110000011000100110010001100110011010000110101001000000010000000100000001010000101010100101001 )
b10010001101000101000000000000 '
b10010001101000101000010110111 (
#70000
b10000 !
b10000 &
b1101111 %
b1000000000000000011101111 "
b1000000000000000011101111 $
b1111000001100010010110000101011001100010011011000100000001000000010000000100000001000000010000000100000001010000100101000101001 )
b10000 '
b1000000000000000011101111 (
#80000
b11111111111111111111111111110000 !
b11111111111111111111111111110000 &
b11111111000111111111000011101111 "
b11111111000111111111000011101111 $
b110001001101100010000000100000001000000010000000100000001000000010000000101000010010100010000001101110011001010110011100101001 )
b11111111111111111111111111110000 '
b11111111000111111111000011101111 (
