processor_core/components/comparator/comparator.v
// ============================================================
// comparator.v : branch comparator for RV32I
// Purpose : compares rs1 and rs2 and decides whether a branch
//           instruction (beq/bne/blt/bge/bltu/bgeu) is taken.
// ============================================================
`timescale 1ns/1ps
module comparator #(
    parameter WIDTH = 32
)(
    input  wire [WIDTH-1:0] a,
    input  wire [WIDTH-1:0] b,
    input  wire [2:0]       funct3,     // branch type from the instruction
    output wire             eq,         // a == b
    output wire             lt,         // a <  b (signed)
    output wire             ltu,        // a <  b (unsigned)
    output reg              taken       // branch condition satisfied
);
    assign eq  = (a == b);
    assign lt  = ($signed(a) < $signed(b));
    assign ltu = (a < b);

    always @(*) begin
        case (funct3)
            3'b000 : taken = eq;        // BEQ
            3'b001 : taken = ~eq;       // BNE
            3'b100 : taken = lt;        // BLT
            3'b101 : taken = ~lt;       // BGE
            3'b110 : taken = ltu;       // BLTU
            3'b111 : taken = ~ltu;      // BGEU
            default: taken = 1'b0;
        endcase
    end
endmodule

processor_core/register_transfer_design/rtl-with-control-unit/rtl/processor_core/components/comparator/comparator-tb.v
`timescale 1ns/1ps
module comparator_tb;
    reg  [31:0] a, b;
    reg  [2:0]  funct3;
    wire eq, lt, ltu, taken;
    integer errors = 0;

    comparator dut (.a(a), .b(b), .funct3(funct3), .eq(eq), .lt(lt), .ltu(ltu), .taken(taken));

    task check(input [2:0] f, input [31:0] x, y, input expected, input [63:0] name);
        begin
            funct3 = f; a = x; b = y; #10;
            if (taken !== expected) begin
                $display("FAIL %0s: a=%h b=%h taken=%b expected=%b", name, x, y, taken, expected);
                errors = errors + 1;
            end else $display("PASS %0s", name);
        end
    endtask

    initial begin
        $dumpfile("comparator.vcd");
        $dumpvars(0, comparator_tb);

        check(3'b000, 32'd5,        32'd5,       1, "BEQ eq");
        check(3'b000, 32'd5,        32'd6,       0, "BEQ ne");
        check(3'b001, 32'd5,        32'd6,       1, "BNE");
        check(3'b100, 32'hFFFFFFFF, 32'd1,       1, "BLT -1<1");
        check(3'b100, 32'd1,        32'hFFFFFFFF,0, "BLT 1<-1");
        check(3'b101, 32'd1,        32'hFFFFFFFF,1, "BGE 1>=-1");
        check(3'b110, 32'hFFFFFFFF, 32'd1,       0, "BLTU big<1");
        check(3'b110, 32'd1,        32'hFFFFFFFF,1, "BLTU 1<big");
        check(3'b111, 32'hFFFFFFFF, 32'd1,       1, "BGEU");
        check(3'b010, 32'd1,        32'd1,       0, "invalid funct3");

        if (errors == 0) $display("COMPARATOR: ALL TESTS PASSED");
        else             $display("COMPARATOR: %0d TEST(S) FAILED", errors);
        $finish;
    end
endmodule

processor_core/components/comparator/comparator.vcd
$date
	Fri Oct  2 11:16:25 2026
$end
$version
	Icarus Verilog
$end
$timescale
	1ps
$end
$scope module comparator_tb $end
$var wire 1 ! taken $end
$var wire 1 " ltu $end
$var wire 1 # lt $end
$var wire 1 $ eq $end
$var reg 32 % a [31:0] $end
$var reg 32 & b [31:0] $end
$var reg 3 ' funct3 [2:0] $end
$var integer 32 ( errors [31:0] $end
$scope module dut $end
$var wire 32 ) a [31:0] $end
$var wire 32 * b [31:0] $end
$var wire 3 + funct3 [2:0] $end
$var wire 1 " ltu $end
$var wire 1 # lt $end
$var wire 1 $ eq $end
$var parameter 32 , WIDTH $end
$var reg 1 ! taken $end
$upscope $end
$scope task check $end
$var reg 1 - expected $end
$var reg 3 . f [2:0] $end
$var reg 64 / name [63:0] $end
$var reg 32 0 x [31:0] $end
$var reg 32 1 y [31:0] $end
$upscope $end
$upscope $end
$enddefinitions $end
$comment Show the parameter values. $end
$dumpall
b100000 ,
$end
#0
$dumpvars
b101 1
b101 0
b10000100100010101010001001000000110010101110001 /
b0 .
1-
b0 +
b101 *
b101 )
b0 (
b0 '
b101 &
b101 %
1$
0#
0"
1!
$end
#10000
0!
0$
1#
1"
b110 &
b110 *
b10000100100010101010001001000000110111001100101 /
0-
b110 1
#20000
1!
b1 '
b1 +
b10000100100111001000101 /
1-
b1 .
#30000
b1 &
b1 *
0"
b11111111111111111111111111111111 %
b11111111111111111111111111111111 )
b100 '
b100 +
b100001001001100010101000010000000101101001100010011110000110001 /
b1 1
b11111111111111111111111111111111 0
b100 .
#40000
0!
1"
b11111111111111111111111111111111 &
b11111111111111111111111111111111 *
0$
0#
b1 %
b1 )
b100001001001100010101000010000000110001001111000010110100110001 /
0-
b11111111111111111111111111111111 1
b1 0
#50000
1!
b101 '
b101 +
b100011101000101001000000011000100111110001111010010110100110001 /
1-
b101 .
#60000
0!
1#
b1 &
b1 *
0$
0"
b11111111111111111111111111111111 %
b11111111111111111111111111111111 )
b110 '
b110 +
b101010001010101001000000110001001101001011001110011110000110001 /
0-
b1 1
b11111111111111111111111111111111 0
b110 .
#70000
1!
1"
b11111111111111111111111111111111 &
b11111111111111111111111111111111 *
0$
0#
b1 %
b1 )
b101010001010101001000000011000100111100011000100110100101100111 /
1-
b11111111111111111111111111111111 1
b1 0
#80000
1#
b1 &
b1 *
0$
0"
b11111111111111111111111111111111 %
b11111111111111111111111111111111 )
b111 '
b111 +
b1000010010001110100010101010101 /
b1 1
b11111111111111111111111111111111 0
b111 .
#90000
0!
1$
0#
b1 %
b1 )
b10 '
b10 +
b110010000100000011001100111010101101110011000110111010000110011 /
0-
b1 0
b10 .
