processor_core/register_transfer_design/rtl-with-control-unit/rtl/processor_core/components/register_files/register-file.v
// ============================================================
// register-file.v : 32 x 32-bit RISC-V register file
// Purpose : the CPU's fast working storage (x0..x31).
//           Two asynchronous read ports (rs1, rs2),
//           one synchronous write port (rd).
//           x0 is hard-wired to zero: reads give 0, writes are ignored.
// ============================================================
`timescale 1ns/1ps
module register_file #(
    parameter WIDTH = 32
)(
    input  wire             clk,
    input  wire             we,          // write enable (RegWrite)
    input  wire [4:0]       rs1_addr,
    input  wire [4:0]       rs2_addr,
    input  wire [4:0]       rd_addr,
    input  wire [WIDTH-1:0] rd_data,
    output wire [WIDTH-1:0] rs1_data,
    output wire [WIDTH-1:0] rs2_data
);
    reg [WIDTH-1:0] regs [0:31];
    integer i;

    initial begin
        for (i = 0; i < 32; i = i + 1) regs[i] = {WIDTH{1'b0}};
    end

    always @(posedge clk) begin
        if (we && rd_addr != 5'd0)
            regs[rd_addr] <= rd_data;
    end

    assign rs1_data = (rs1_addr == 5'd0) ? {WIDTH{1'b0}} : regs[rs1_addr];
    assign rs2_data = (rs2_addr == 5'd0) ? {WIDTH{1'b0}} : regs[rs2_addr];
endmodule

processor_core/components/register_files/register-file-tb.v
`timescale 1ns/1ps
module register_file_tb;
    reg         clk = 0, we = 0;
    reg  [4:0]  rs1_addr = 0, rs2_addr = 0, rd_addr = 0;
    reg  [31:0] rd_data = 0;
    wire [31:0] rs1_data, rs2_data;
    integer errors = 0, i;

    register_file dut (.clk(clk), .we(we), .rs1_addr(rs1_addr), .rs2_addr(rs2_addr),
                       .rd_addr(rd_addr), .rd_data(rd_data),
                       .rs1_data(rs1_data), .rs2_data(rs2_data));
    always #5 clk = ~clk;

    task write_reg(input [4:0] r, input [31:0] v);
        begin
            we = 1; rd_addr = r; rd_data = v;
            @(posedge clk); #1;
            we = 0;
        end
    endtask

    task check_read(input [4:0] r1, r2, input [31:0] e1, e2, input [127:0] name);
        begin
            rs1_addr = r1; rs2_addr = r2; #1;
            if (rs1_data !== e1 || rs2_data !== e2) begin
                $display("FAIL %0s: got %h,%h expected %h,%h", name, rs1_data, rs2_data, e1, e2);
                errors = errors + 1;
            end else $display("PASS %0s", name);
        end
    endtask

    initial begin
        $dumpfile("register_file.vcd");
        $dumpvars(0, register_file_tb);

        write_reg(5'd1, 32'hAAAA_0001);
        write_reg(5'd2, 32'hBBBB_0002);
        check_read(5'd1, 5'd2, 32'hAAAA_0001, 32'hBBBB_0002, "two read ports");

        write_reg(5'd0, 32'hFFFF_FFFF);
        check_read(5'd0, 5'd0, 32'h0, 32'h0, "x0 stays zero");

        // write disabled: value must not change
        we = 0; rd_addr = 5'd1; rd_data = 32'h1111_1111;
        @(posedge clk); #1;
        check_read(5'd1, 5'd2, 32'hAAAA_0001, 32'hBBBB_0002, "no write when we=0");

        // fill all registers and read back
        for (i = 1; i < 32; i = i + 1) write_reg(i[4:0], 32'h1000 + i);
        for (i = 1; i < 32; i = i + 1) begin
            rs1_addr = i[4:0]; #1;
            if (rs1_data !== 32'h1000 + i) begin
                $display("FAIL x%0d = %h", i, rs1_data); errors = errors + 1;
            end
        end
        $display("Checked x1..x31 read-back");

        if (errors == 0) $display("REGISTER FILE: ALL TESTS PASSED");
        else             $display("REGISTER FILE: %0d TEST(S) FAILED", errors);
        $finish;
    end
endmodule

processor_core/components/register_files/register_file.vcd
$date
	Fri Oct  2 11:16:25 2026
$end
$version
	Icarus Verilog
$end
$timescale
	1ps
$end
$scope module register_file_tb $end
$var wire 32 ! rs2_data [31:0] $end
$var wire 32 " rs1_data [31:0] $end
$var reg 1 # clk $end
$var reg 5 $ rd_addr [4:0] $end
$var reg 32 % rd_data [31:0] $end
$var reg 5 & rs1_addr [4:0] $end
$var reg 5 ' rs2_addr [4:0] $end
$var reg 1 ( we $end
$var integer 32 ) errors [31:0] $end
$var integer 32 * i [31:0] $end
$scope module dut $end
$var wire 1 # clk $end
$var wire 5 + rd_addr [4:0] $end
$var wire 32 , rd_data [31:0] $end
$var wire 5 - rs1_addr [4:0] $end
$var wire 5 . rs2_addr [4:0] $end
$var wire 1 ( we $end
$var wire 32 / rs2_data [31:0] $end
$var wire 32 0 rs1_data [31:0] $end
$var parameter 32 1 WIDTH $end
$var integer 32 2 i [31:0] $end
$upscope $end
$scope task check_read $end
$var reg 32 3 e1 [31:0] $end
$var reg 32 4 e2 [31:0] $end
$var reg 128 5 name [127:0] $end
$var reg 5 6 r1 [4:0] $end
$var reg 5 7 r2 [4:0] $end
$upscope $end
$scope task write_reg $end
$var reg 5 8 r [4:0] $end
$var reg 32 9 v [31:0] $end
$upscope $end
$upscope $end
$enddefinitions $end
$comment Show the parameter values. $end
$dumpall
b100000 1
$end
#0
$dumpvars
b10101010101010100000000000000001 9
b1 8
bx 7
bx 6
bx 5
bx 4
bx 3
b100000 2
b0 0
b0 /
b0 .
b0 -
b10101010101010100000000000000001 ,
b1 +
bx *
b0 )
1(
b0 '
b0 &
b10101010101010100000000000000001 %
b1 $
0#
b0 "
b0 !
$end
#5000
1#
#6000
b10111011101110110000000000000010 %
b10111011101110110000000000000010 ,
b10 $
b10 +
b10111011101110110000000000000010 9
b10 8
1(
#10000
0#
#15000
1#
#16000
b10111011101110110000000000000010 !
b10111011101110110000000000000010 /
b10101010101010100000000000000001 "
b10101010101010100000000000000001 0
b10 '
b10 .
b1 &
b1 -
b111010001110111011011110010000001110010011001010110000101100100001000000111000001101111011100100111010001110011 5
b10111011101110110000000000000010 4
b10101010101010100000000000000001 3
b10 7
b1 6
0(
#17000
b11111111111111111111111111111111 %
b11111111111111111111111111111111 ,
b0 $
b0 +
1(
b11111111111111111111111111111111 9
b0 8
#20000
0#
#25000
1#
#26000
b0 !
b0 /
b0 "
b0 0
b0 '
b0 .
b0 &
b0 -
b1111000001100000010000001110011011101000110000101111001011100110010000001111010011001010111001001101111 5
b0 4
b0 3
b0 7
b0 6
0(
#27000
b10001000100010001000100010001 %
b10001000100010001000100010001 ,
b1 $
b1 +
#30000
0#
#35000
1#
#36000
b10111011101110110000000000000010 !
b10111011101110110000000000000010 /
b10101010101010100000000000000001 "
b10101010101010100000000000000001 0
b10 '
b10 .
b1 &
b1 -
b100000011101110111001001101001011101000110010100100000011101110110100001100101011011100010000001110111011001010011110100110000 5
b10111011101110110000000000000010 4
b10101010101010100000000000000001 3
b10 7
b1 6
#37000
b1000000000001 %
b1000000000001 ,
1(
b1000000000001 9
b1 8
b1 *
#40000
0#
#45000
b1000000000001 "
b1000000000001 0
1#
#46000
b1000000000010 %
b1000000000010 ,
b10 $
b10 +
b1000000000010 9
b10 8
b10 *
1(
#50000
0#
#55000
b1000000000010 !
b1000000000010 /
1#
#56000
b1000000000011 %
b1000000000011 ,
b11 $
b11 +
b1000000000011 9
b11 8
b11 *
1(
#60000
0#
#65000
1#
#66000
b1000000000100 %
b1000000000100 ,
b100 $
b100 +
b1000000000100 9
b100 8
b100 *
1(
#70000
0#
#75000
1#
#76000
b1000000000101 %
b1000000000101 ,
b101 $
b101 +
b1000000000101 9
b101 8
b101 *
1(
#80000
0#
#85000
1#
#86000
b1000000000110 %
b1000000000110 ,
b110 $
b110 +
b1000000000110 9
b110 8
b110 *
1(
#90000
0#
#95000
1#
#96000
b1000000000111 %
b1000000000111 ,
b111 $
b111 +
b1000000000111 9
b111 8
b111 *
1(
#100000
0#
#105000
1#
#106000
b1000000001000 %
b1000000001000 ,
b1000 $
b1000 +
b1000000001000 9
b1000 8
b1000 *
1(
#110000
0#
#115000
1#
#116000
b1000000001001 %
b1000000001001 ,
b1001 $
b1001 +
b1000000001001 9
b1001 8
b1001 *
1(
#120000
0#
#125000
1#
#126000
b1000000001010 %
b1000000001010 ,
b1010 $
b1010 +
b1000000001010 9
b1010 8
b1010 *
1(
#130000
0#
#135000
1#
#136000
b1000000001011 %
b1000000001011 ,
b1011 $
b1011 +
b1000000001011 9
b1011 8
b1011 *
1(
#140000
0#
#145000
1#
#146000
b1000000001100 %
b1000000001100 ,
b1100 $
b1100 +
b1000000001100 9
b1100 8
b1100 *
1(
#150000
0#
#155000
1#
#156000
b1000000001101 %
b1000000001101 ,
b1101 $
b1101 +
b1000000001101 9
b1101 8
b1101 *
1(
#160000
0#
#165000
1#
#166000
b1000000001110 %
b1000000001110 ,
b1110 $
b1110 +
b1000000001110 9
b1110 8
b1110 *
1(
#170000
0#
#175000
1#
#176000
b1000000001111 %
b1000000001111 ,
b1111 $
b1111 +
b1000000001111 9
b1111 8
b1111 *
1(
#180000
0#
#185000
1#
#186000
b1000000010000 %
b1000000010000 ,
b10000 $
b10000 +
b1000000010000 9
b10000 8
b10000 *
1(
#190000
0#
#195000
1#
#196000
b1000000010001 %
b1000000010001 ,
b10001 $
b10001 +
b1000000010001 9
b10001 8
b10001 *
1(
#200000
0#
#205000
1#
#206000
b1000000010010 %
b1000000010010 ,
b10010 $
b10010 +
b1000000010010 9
b10010 8
b10010 *
1(
#210000
0#
#215000
1#
#216000
b1000000010011 %
b1000000010011 ,
b10011 $
b10011 +
b1000000010011 9
b10011 8
b10011 *
1(
#220000
0#
#225000
1#
#226000
b1000000010100 %
b1000000010100 ,
b10100 $
b10100 +
b1000000010100 9
b10100 8
b10100 *
1(
#230000
0#
#235000
1#
#236000
b1000000010101 %
b1000000010101 ,
b10101 $
b10101 +
b1000000010101 9
b10101 8
b10101 *
1(
#240000
0#
#245000
1#
#246000
b1000000010110 %
b1000000010110 ,
b10110 $
b10110 +
b1000000010110 9
b10110 8
b10110 *
1(
#250000
0#
#255000
1#
#256000
b1000000010111 %
b1000000010111 ,
b10111 $
b10111 +
b1000000010111 9
b10111 8
b10111 *
1(
#260000
0#
#265000
1#
#266000
b1000000011000 %
b1000000011000 ,
b11000 $
b11000 +
b1000000011000 9
b11000 8
b11000 *
1(
#270000
0#
#275000
1#
#276000
b1000000011001 %
b1000000011001 ,
b11001 $
b11001 +
b1000000011001 9
b11001 8
b11001 *
1(
#280000
0#
#285000
1#
#286000
b1000000011010 %
b1000000011010 ,
b11010 $
b11010 +
b1000000011010 9
b11010 8
b11010 *
1(
#290000
0#
#295000
1#
#296000
b1000000011011 %
b1000000011011 ,
b11011 $
b11011 +
b1000000011011 9
b11011 8
b11011 *
1(
#300000
0#
#305000
1#
#306000
b1000000011100 %
b1000000011100 ,
b11100 $
b11100 +
b1000000011100 9
b11100 8
b11100 *
1(
#310000
0#
#315000
1#
#316000
b1000000011101 %
b1000000011101 ,
b11101 $
b11101 +
b1000000011101 9
b11101 8
b11101 *
1(
#320000
0#
#325000
1#
#326000
b1000000011110 %
b1000000011110 ,
b11110 $
b11110 +
b1000000011110 9
b11110 8
b11110 *
1(
#330000
0#
#335000
1#
#336000
b1000000011111 %
b1000000011111 ,
b11111 $
b11111 +
b1000000011111 9
b11111 8
b11111 *
1(
#340000
0#
#345000
1#
#346000
b1 *
0(
#347000
b1000000000010 "
b1000000000010 0
b10 &
b10 -
b10 *
#348000
b1000000000011 "
b1000000000011 0
b11 &
b11 -
b11 *
#349000
b1000000000100 "
b1000000000100 0
b100 &
b100 -
b100 *
#350000
b1000000000101 "
b1000000000101 0
b101 &
b101 -
b101 *
0#
#351000
b1000000000110 "
b1000000000110 0
b110 &
b110 -
b110 *
#352000
b1000000000111 "
b1000000000111 0
b111 &
b111 -
b111 *
#353000
b1000000001000 "
b1000000001000 0
b1000 &
b1000 -
b1000 *
#354000
b1000000001001 "
b1000000001001 0
b1001 &
b1001 -
b1001 *
#355000
b1000000001010 "
b1000000001010 0
b1010 &
b1010 -
b1010 *
1#
#356000
b1000000001011 "
b1000000001011 0
b1011 &
b1011 -
b1011 *
#357000
b1000000001100 "
b1000000001100 0
b1100 &
b1100 -
b1100 *
#358000
b1000000001101 "
b1000000001101 0
b1101 &
b1101 -
b1101 *
#359000
b1000000001110 "
b1000000001110 0
b1110 &
b1110 -
b1110 *
#360000
b1000000001111 "
b1000000001111 0
b1111 &
b1111 -
b1111 *
0#
#361000
b1000000010000 "
b1000000010000 0
b10000 &
b10000 -
b10000 *
#362000
b1000000010001 "
b1000000010001 0
b10001 &
b10001 -
b10001 *
#363000
b1000000010010 "
b1000000010010 0
b10010 &
b10010 -
b10010 *
#364000
b1000000010011 "
b1000000010011 0
b10011 &
b10011 -
b10011 *
#365000
b1000000010100 "
b1000000010100 0
b10100 &
b10100 -
b10100 *
1#
#366000
b1000000010101 "
b1000000010101 0
b10101 &
b10101 -
b10101 *
#367000
b1000000010110 "
b1000000010110 0
b10110 &
b10110 -
b10110 *
#368000
b1000000010111 "
b1000000010111 0
b10111 &
b10111 -
b10111 *
#369000
b1000000011000 "
b1000000011000 0
b11000 &
b11000 -
b11000 *
#370000
b1000000011001 "
b1000000011001 0
b11001 &
b11001 -
b11001 *
0#
#371000
b1000000011010 "
b1000000011010 0
b11010 &
b11010 -
b11010 *
#372000
b1000000011011 "
b1000000011011 0
b11011 &
b11011 -
b11011 *
#373000
b1000000011100 "
b1000000011100 0
b11100 &
b11100 -
b11100 *
#374000
b1000000011101 "
b1000000011101 0
b11101 &
b11101 -
b11101 *
#375000
b1000000011110 "
b1000000011110 0
b11110 &
b11110 -
b11110 *
1#
#376000
b1000000011111 "
b1000000011111 0
b11111 &
b11111 -
b11111 *
#377000
b100000 *
